{"v":"5.7.3","fr":60,"ip":0,"op":300,"w":600,"h":600,"nm":"Defuse 5 Sec","ddd":0,"assets":[],"layers":[{"ddd":0,"ind":1,"ty":4,"nm":"OBJECTS/124372-OQT5KA-344 Outlines 2","sr":1,"ks":{"o":{"a":1,"k":[{"i":{"x":[0.667],"y":[1]},"o":{"x":[0.333],"y":[0]},"t":25,"s":[0]},{"i":{"x":[0.57],"y":[1]},"o":{"x":[0.194],"y":[0]},"t":68,"s":[100]},{"i":{"x":[0.663],"y":[1]},"o":{"x":[0.329],"y":[0]},"t":271,"s":[100]},{"i":{"x":[0.704],"y":[1]},"o":{"x":[0.336],"y":[0]},"t":299,"s":[0]},{"i":{"x":[0.667],"y":[1]},"o":{"x":[0.333],"y":[0]},"t":574,"s":[100]},{"t":599,"s":[0]}],"ix":11},"r":{"a":1,"k":[{"i":{"x":[0.667],"y":[1]},"o":{"x":[0.333],"y":[0]},"t":26,"s":[0]},{"i":{"x":[0.833],"y":[1]},"o":{"x":[0.167],"y":[0]},"t":47,"s":[22]},{"i":{"x":[0.833],"y":[1]},"o":{"x":[0.167],"y":[0]},"t":106,"s":[22]},{"i":{"x":[0.833],"y":[1]},"o":{"x":[0.167],"y":[0]},"t":131,"s":[0]},{"i":{"x":[0.833],"y":[1]},"o":{"x":[0.167],"y":[0]},"t":156,"s":[22]},{"i":{"x":[0.833],"y":[1]},"o":{"x":[0.167],"y":[0]},"t":242,"s":[22]},{"i":{"x":[0.833],"y":[1]},"o":{"x":[0.167],"y":[0]},"t":267,"s":[0]},{"i":{"x":[0.833],"y":[1]},"o":{"x":[0.167],"y":[0]},"t":292,"s":[22]},{"i":{"x":[0.833],"y":[1]},"o":{"x":[0.167],"y":[0]},"t":366,"s":[22]},{"i":{"x":[0.833],"y":[1]},"o":{"x":[0.167],"y":[0]},"t":391,"s":[0]},{"i":{"x":[0.833],"y":[1]},"o":{"x":[0.167],"y":[0]},"t":416,"s":[22]},{"i":{"x":[0.833],"y":[1]},"o":{"x":[0.167],"y":[0]},"t":486,"s":[22]},{"i":{"x":[0.833],"y":[1]},"o":{"x":[0.167],"y":[0]},"t":511,"s":[0]},{"t":536,"s":[22]}],"ix":10},"p":{"a":1,"k":[{"i":{"x":0.667,"y":1},"o":{"x":0.333,"y":0},"t":271,"s":[306.5,263.5,0],"to":[0,0,0],"ti":[0,0,0]},{"i":{"x":0.667,"y":1},"o":{"x":0.333,"y":0},"t":299,"s":[306.5,334,0],"to":[0,0,0],"ti":[0,0,0]},{"i":{"x":0.667,"y":1},"o":{"x":0.333,"y":0},"t":574,"s":[306.5,263.5,0],"to":[0,8.333,0],"ti":[0,-8.333,0]},{"t":599,"s":[306.5,313.5,0]}],"ix":2},"a":{"a":0,"k":[322.865,73.657,0],"ix":1},"s":{"a":0,"k":[-162.279,162.279,100],"ix":6}},"ao":0,"shapes":[{"ty":"gr","it":[{"ind":0,"ty":"sh","ix":1,"ks":{"a":0,"k":{"i":[[0,0],[-11.774,26.268],[30.047,-9.446],[-17.302,18.855],[25.212,0.615],[-18.179,8.123],[20.506,7.719],[-15.138,-0.063],[11.712,7.163],[-3.665,-2.256],[3.584,3.661],[0.901,-0.26],[-0.057,1.328],[0,0],[-3.828,43.457],[25.4,-18.676]],"o":[[29.731,-16.121],[10.375,35.687],[23.009,-2.264],[-1.155,30.221],[16.75,3.325],[-10.291,21.511],[11.145,5.914],[-11.381,9.588],[2.778,2.544],[-5.96,0.916],[-0.553,2.439],[1.561,-8.839],[0.058,-1.329],[40.464,-24.638],[21.682,30.601],[0,0]],"v":[[-16.957,24.953],[33.332,-32.193],[-27.418,33.35],[30.477,2.453],[-33.482,36.828],[17.423,29.461],[-39.444,39.202],[-0.655,47.791],[-36.719,47.502],[-27.074,54.663],[-41.487,49.584],[-43.707,54.245],[-43.186,40.264],[-41.799,37.837],[19.676,-57.379],[-16.964,24.955]],"c":true},"ix":2},"nm":"Path 1","mn":"ADBE Vector Shape - Group","hd":false},{"ty":"fl","c":{"a":0,"k":[1,1,1,1],"ix":4},"o":{"a":0,"k":100,"ix":5},"r":1,"bm":0,"nm":"Fill 1","mn":"ADBE Vector Graphic - Fill","hd":false},{"ty":"tr","p":{"a":0,"k":[392.245,103.176],"ix":2},"a":{"a":0,"k":[0,0],"ix":1},"s":{"a":0,"k":[100,100],"ix":3},"r":{"a":0,"k":0,"ix":6},"o":{"a":0,"k":100,"ix":7},"sk":{"a":0,"k":0,"ix":4},"sa":{"a":0,"k":0,"ix":5},"nm":"Transform"}],"nm":"Group 8","np":2,"cix":2,"bm":0,"ix":1,"mn":"ADBE Vector Group","hd":false}],"ip":0,"op":602,"st":0,"bm":0},{"ddd":0,"ind":2,"ty":4,"nm":"Layer 1/6039 [Converted] Outlines 2","sr":1,"ks":{"o":{"a":1,"k":[{"i":{"x":[0.667],"y":[1]},"o":{"x":[0.333],"y":[0]},"t":0,"s":[0]},{"i":{"x":[0.572],"y":[1]},"o":{"x":[0.189],"y":[0]},"t":25,"s":[100]},{"i":{"x":[0.664],"y":[1]},"o":{"x":[0.331],"y":[0]},"t":271,"s":[100]},{"i":{"x":[0.703],"y":[1]},"o":{"x":[0.34],"y":[0]},"t":299,"s":[0]},{"i":{"x":[0.667],"y":[1]},"o":{"x":[0.333],"y":[0]},"t":574,"s":[100]},{"t":599,"s":[0]}],"ix":11},"r":{"a":1,"k":[{"i":{"x":[0.667],"y":[1]},"o":{"x":[0.333],"y":[0]},"t":26,"s":[0]},{"i":{"x":[0.833],"y":[1]},"o":{"x":[0.167],"y":[0]},"t":47,"s":[-20]},{"i":{"x":[0.833],"y":[1]},"o":{"x":[0.167],"y":[0]},"t":106,"s":[-20]},{"i":{"x":[0.833],"y":[1]},"o":{"x":[0.167],"y":[0]},"t":131,"s":[0]},{"i":{"x":[0.833],"y":[1]},"o":{"x":[0.167],"y":[0]},"t":156,"s":[-20]},{"i":{"x":[0.833],"y":[1]},"o":{"x":[0.167],"y":[0]},"t":242,"s":[-20]},{"i":{"x":[0.833],"y":[1]},"o":{"x":[0.167],"y":[0]},"t":267,"s":[0]},{"i":{"x":[0.833],"y":[1]},"o":{"x":[0.167],"y":[0]},"t":292,"s":[-20]},{"i":{"x":[0.833],"y":[1]},"o":{"x":[0.167],"y":[0]},"t":366,"s":[-20]},{"i":{"x":[0.833],"y":[1]},"o":{"x":[0.167],"y":[0]},"t":391,"s":[0]},{"i":{"x":[0.833],"y":[1]},"o":{"x":[0.167],"y":[0]},"t":416,"s":[-20]},{"i":{"x":[0.833],"y":[1]},"o":{"x":[0.167],"y":[0]},"t":486,"s":[-20]},{"i":{"x":[0.833],"y":[1]},"o":{"x":[0.167],"y":[0]},"t":511,"s":[0]},{"t":536,"s":[-20]}],"ix":10},"p":{"a":1,"k":[{"i":{"x":0.667,"y":1},"o":{"x":0.333,"y":0},"t":0,"s":[307.532,425.458,0],"to":[0,-26.833,0],"ti":[0,26.833,0]},{"i":{"x":0.572,"y":0.572},"o":{"x":0.189,"y":0.189},"t":25,"s":[307.532,264.458,0],"to":[0,0,0],"ti":[0,0,0]},{"i":{"x":0.664,"y":1},"o":{"x":0.331,"y":0},"t":271,"s":[307.532,264.458,0],"to":[0,0,0],"ti":[0,0,0]},{"i":{"x":0.703,"y":1},"o":{"x":0.34,"y":0},"t":299,"s":[307.532,334.958,0],"to":[0,0,0],"ti":[0,0,0]},{"i":{"x":0.667,"y":1},"o":{"x":0.333,"y":0},"t":574,"s":[307.532,264.458,0],"to":[0,8.333,0],"ti":[0,-8.333,0]},{"t":599,"s":[307.532,314.458,0]}],"ix":2},"a":{"a":0,"k":[181.761,71.792,0],"ix":1},"s":{"a":0,"k":[-182.417,182.417,100],"ix":6}},"ao":0,"shapes":[{"ty":"gr","it":[{"ind":0,"ty":"sh","ix":1,"ks":{"a":0,"k":{"i":[[0.544,2.333],[0,21.464],[-2.384,7.777],[1.068,0.323],[0,-11.716],[-0.185,-0.792],[-2.798,0],[-0.47,0.109],[-0.045,0.011]],"o":[[-0.185,-0.792],[0,-11.107],[-0.665,-0.558],[-2.457,8.455],[0,21.464],[0.663,2.843],[0.463,0],[0.045,-0.011],[-2.175,-0.539]],"v":[[1.499,26.55],[-3.029,-5.326],[2.144,-30.018],[-0.468,-31.312],[-6.029,-5.326],[-1.501,26.55],[4.492,31.312],[5.895,31.15],[6.028,31.113]],"c":true},"ix":2},"nm":"Path 1","mn":"ADBE Vector Shape - Group","hd":false},{"ty":"fl","c":{"a":0,"k":[0.019999999626,0.035000000748,0.059000000299,1],"ix":4},"o":{"a":0,"k":100,"ix":5},"r":1,"bm":0,"nm":"Fill 1","mn":"ADBE Vector Graphic - Fill","hd":false},{"ty":"tr","p":{"a":0,"k":[166.826,132.873],"ix":2},"a":{"a":0,"k":[0,0],"ix":1},"s":{"a":0,"k":[100,100],"ix":3},"r":{"a":0,"k":0,"ix":6},"o":{"a":0,"k":100,"ix":7},"sk":{"a":0,"k":0,"ix":4},"sa":{"a":0,"k":0,"ix":5},"nm":"Transform"}],"nm":"Group 82","np":2,"cix":2,"bm":0,"ix":1,"mn":"ADBE Vector Group","hd":false},{"ty":"gr","it":[{"ind":0,"ty":"sh","ix":1,"ks":{"a":0,"k":{"i":[[-0.185,-0.792],[-2.798,0],[-0.47,0.109],[0.77,3.314],[0.464,1.536],[1.211,6.816],[0,8.743],[-1.498,4.691],[3.481,1.053],[0,-11.716]],"o":[[0.663,2.843],[0.463,0],[3.312,-0.773],[-0.012,-0.05],[-4.264,1.281],[-0.883,-4.971],[0,-6.967],[1.562,-4.891],[-2.457,8.455],[0,21.464]],"v":[[-4.12,26.55],[1.872,31.312],[3.275,31.15],[7.878,23.753],[7.077,21.374],[-0.849,14.667],[-2.489,-5.84],[0.332,-23.372],[-3.088,-31.312],[-8.648,-5.326]],"c":true},"ix":2},"nm":"Path 1","mn":"ADBE Vector Shape - Group","hd":false},{"ty":"fl","c":{"a":0,"k":[0.059000000299,0.109999997008,0.19199999641,1],"ix":4},"o":{"a":0,"k":100,"ix":5},"r":1,"bm":0,"nm":"Fill 1","mn":"ADBE Vector Graphic - Fill","hd":false},{"ty":"tr","p":{"a":0,"k":[169.446,132.873],"ix":2},"a":{"a":0,"k":[0,0],"ix":1},"s":{"a":0,"k":[100,100],"ix":3},"r":{"a":0,"k":0,"ix":6},"o":{"a":0,"k":100,"ix":7},"sk":{"a":0,"k":0,"ix":4},"sa":{"a":0,"k":0,"ix":5},"nm":"Transform"}],"nm":"Group 83","np":2,"cix":2,"bm":0,"ix":2,"mn":"ADBE Vector Group","hd":false},{"ty":"gr","it":[{"ind":0,"ty":"sh","ix":1,"ks":{"a":0,"k":{"i":[[-0.062,0.266],[-0.084,2.463],[2.359,0],[0,-1.712],[0,-0.754],[0,0],[1.522,-5.237],[0,-11.716],[-0.184,-0.792],[-2.799,0],[-0.469,0.11],[-0.402,0.195],[0,21.107]],"o":[[0.383,-1.633],[-1.765,-0.48],[-1.118,0],[0,1.955],[0,0],[0,0.385],[-2.457,8.456],[0,21.464],[0.664,2.843],[0.463,0],[0.454,-0.105],[-1.111,-3.144],[0,-20.635]],"v":[[8.764,-33.332],[9.41,-39.856],[0.32,-41.105],[-1.976,-38.893],[-4.985,-33.871],[-4.985,-31.818],[-3.848,-21.519],[-9.41,4.467],[-4.882,36.344],[1.112,41.105],[2.514,40.943],[3.797,40.486],[-1.078,4.237]],"c":true},"ix":2},"nm":"Path 1","mn":"ADBE Vector Shape - Group","hd":false},{"ty":"fl","c":{"a":0,"k":[1,1,1,1],"ix":4},"o":{"a":0,"k":100,"ix":5},"r":1,"bm":0,"nm":"Fill 1","mn":"ADBE Vector Graphic - Fill","hd":false},{"ty":"tr","p":{"a":0,"k":[170.207,123.08],"ix":2},"a":{"a":0,"k":[0,0],"ix":1},"s":{"a":0,"k":[100,100],"ix":3},"r":{"a":0,"k":0,"ix":6},"o":{"a":0,"k":100,"ix":7},"sk":{"a":0,"k":0,"ix":4},"sa":{"a":0,"k":0,"ix":5},"nm":"Transform"}],"nm":"Group 84","np":2,"cix":2,"bm":0,"ix":3,"mn":"ADBE Vector Group","hd":false},{"ty":"gr","it":[{"ind":0,"ty":"sh","ix":1,"ks":{"a":0,"k":{"i":[[0.211,-12.255],[0,0],[0,0],[0,0],[0,0]],"o":[[0,0],[0,0],[0,0],[0,0],[3.358,16.887]],"v":[[3.701,25.29],[4.29,25.056],[4.633,16.377],[-4.351,-25.29],[-4.632,-25.29]],"c":true},"ix":2},"nm":"Path 1","mn":"ADBE Vector Shape - Group","hd":false},{"ty":"fl","c":{"a":0,"k":[0.552999997606,0.57599995931,0.6,1],"ix":4},"o":{"a":0,"k":100,"ix":5},"r":1,"bm":0,"nm":"Fill 1","mn":"ADBE Vector Graphic - Fill","hd":false},{"ty":"tr","p":{"a":0,"k":[187.712,43.657],"ix":2},"a":{"a":0,"k":[0,0],"ix":1},"s":{"a":0,"k":[100,100],"ix":3},"r":{"a":0,"k":0,"ix":6},"o":{"a":0,"k":100,"ix":7},"sk":{"a":0,"k":0,"ix":4},"sa":{"a":0,"k":0,"ix":5},"nm":"Transform"}],"nm":"Group 85","np":2,"cix":2,"bm":0,"ix":4,"mn":"ADBE Vector Group","hd":false},{"ty":"gr","it":[{"ind":0,"ty":"sh","ix":1,"ks":{"a":0,"k":{"i":[[0,-2.209],[2.209,0],[0,2.209],[-2.209,0]],"o":[[0,2.209],[-2.209,0],[0,-2.209],[2.209,0]],"v":[[4,0],[0,4],[-4,0],[0,-4]],"c":true},"ix":2},"nm":"Path 1","mn":"ADBE Vector Shape - Group","hd":false},{"ty":"fl","c":{"a":0,"k":[0.677999997606,0.705999995213,0.728999956916,1],"ix":4},"o":{"a":0,"k":100,"ix":5},"r":1,"bm":0,"nm":"Fill 1","mn":"ADBE Vector Graphic - Fill","hd":false},{"ty":"tr","p":{"a":0,"k":[181.692,71.559],"ix":2},"a":{"a":0,"k":[0,0],"ix":1},"s":{"a":0,"k":[100,100],"ix":3},"r":{"a":0,"k":0,"ix":6},"o":{"a":0,"k":100,"ix":7},"sk":{"a":0,"k":0,"ix":4},"sa":{"a":0,"k":0,"ix":5},"nm":"Transform"}],"nm":"Group 86","np":2,"cix":2,"bm":0,"ix":5,"mn":"ADBE Vector Group","hd":false},{"ty":"gr","it":[{"ind":0,"ty":"sh","ix":1,"ks":{"a":0,"k":{"i":[[2.757,0],[0,2.758],[-2.757,0],[0,-2.758]],"o":[[-2.757,0],[0,-2.758],[2.757,0],[0,2.758]],"v":[[0,5],[-5,0],[0,-5],[5,0]],"c":true},"ix":2},"nm":"Path 1","mn":"ADBE Vector Shape - Group","hd":false},{"ty":"fl","c":{"a":0,"k":[0.552999997606,0.57599995931,0.6,1],"ix":4},"o":{"a":0,"k":100,"ix":5},"r":1,"bm":0,"nm":"Fill 1","mn":"ADBE Vector Graphic - Fill","hd":false},{"ty":"tr","p":{"a":0,"k":[181.692,71.559],"ix":2},"a":{"a":0,"k":[0,0],"ix":1},"s":{"a":0,"k":[100,100],"ix":3},"r":{"a":0,"k":0,"ix":6},"o":{"a":0,"k":100,"ix":7},"sk":{"a":0,"k":0,"ix":4},"sa":{"a":0,"k":0,"ix":5},"nm":"Transform"}],"nm":"Group 87","np":2,"cix":2,"bm":0,"ix":6,"mn":"ADBE Vector Group","hd":false},{"ty":"gr","it":[{"ind":0,"ty":"sh","ix":1,"ks":{"a":0,"k":{"i":[[0,-5.215],[5.215,0],[0,5.215],[-5.215,0]],"o":[[0,5.215],[-5.215,0],[0,-5.215],[5.215,0]],"v":[[9.443,0],[0,9.443],[-9.443,0],[0,-9.443]],"c":true},"ix":2},"nm":"Path 1","mn":"ADBE Vector Shape - Group","hd":false},{"ty":"fl","c":{"a":0,"k":[0.677999997606,0.705999995213,0.728999956916,1],"ix":4},"o":{"a":0,"k":100,"ix":5},"r":1,"bm":0,"nm":"Fill 1","mn":"ADBE Vector Graphic - Fill","hd":false},{"ty":"tr","p":{"a":0,"k":[181.692,71.559],"ix":2},"a":{"a":0,"k":[0,0],"ix":1},"s":{"a":0,"k":[100,100],"ix":3},"r":{"a":0,"k":0,"ix":6},"o":{"a":0,"k":100,"ix":7},"sk":{"a":0,"k":0,"ix":4},"sa":{"a":0,"k":0,"ix":5},"nm":"Transform"}],"nm":"Group 88","np":2,"cix":2,"bm":0,"ix":7,"mn":"ADBE Vector Group","hd":false},{"ty":"gr","it":[{"ind":0,"ty":"sh","ix":1,"ks":{"a":0,"k":{"i":[[4.578,0.224],[0,0],[0,0]],"o":[[0,0],[0,0],[-1.167,-4.268]],"v":[[-4.775,-5.736],[-4.775,5.736],[4.775,1.932]],"c":true},"ix":2},"nm":"Path 1","mn":"ADBE Vector Shape - Group","hd":false},{"ty":"fl","c":{"a":0,"k":[0.552999997606,0.57599995931,0.6,1],"ix":4},"o":{"a":0,"k":100,"ix":5},"r":1,"bm":0,"nm":"Fill 1","mn":"ADBE Vector Graphic - Fill","hd":false},{"ty":"tr","p":{"a":0,"k":[186.981,66.878],"ix":2},"a":{"a":0,"k":[0,0],"ix":1},"s":{"a":0,"k":[100,100],"ix":3},"r":{"a":0,"k":0,"ix":6},"o":{"a":0,"k":100,"ix":7},"sk":{"a":0,"k":0,"ix":4},"sa":{"a":0,"k":0,"ix":5},"nm":"Transform"}],"nm":"Group 89","np":2,"cix":2,"bm":0,"ix":8,"mn":"ADBE Vector Group","hd":false},{"ty":"gr","it":[{"ind":0,"ty":"sh","ix":1,"ks":{"a":0,"k":{"i":[[-3.278,-0.657],[0,0],[0,0]],"o":[[0,0],[0,0],[1.39,2.948]],"v":[[3.693,4.592],[3.693,-4.592],[-3.693,-1.213]],"c":true},"ix":2},"nm":"Path 1","mn":"ADBE Vector Shape - Group","hd":false},{"ty":"fl","c":{"a":0,"k":[0.552999997606,0.57599995931,0.6,1],"ix":4},"o":{"a":0,"k":100,"ix":5},"r":1,"bm":0,"nm":"Fill 1","mn":"ADBE Vector Graphic - Fill","hd":false},{"ty":"tr","p":{"a":0,"k":[175.944,77.206],"ix":2},"a":{"a":0,"k":[0,0],"ix":1},"s":{"a":0,"k":[100,100],"ix":3},"r":{"a":0,"k":0,"ix":6},"o":{"a":0,"k":100,"ix":7},"sk":{"a":0,"k":0,"ix":4},"sa":{"a":0,"k":0,"ix":5},"nm":"Transform"}],"nm":"Group 90","np":2,"cix":2,"bm":0,"ix":9,"mn":"ADBE Vector Group","hd":false},{"ty":"gr","it":[{"ind":0,"ty":"sh","ix":1,"ks":{"a":0,"k":{"i":[[0.463,0],[0.663,2.843],[0,21.464],[-2.457,8.455],[0,0.386],[0,0],[0,1.954],[-1.117,0],[-1.236,-0.456],[0,-1.544],[0.586,-2.496],[0,-16.75],[-0.043,-0.18],[3.312,-0.773]],"o":[[-2.798,0],[-0.185,-0.792],[0,-11.716],[1.522,-5.237],[0,0],[0,-0.753],[0,-1.713],[2.574,0],[0.89,0.329],[0,2.961],[-0.05,0.216],[0,19.993],[0.769,3.314],[-0.47,0.109]],"v":[[0.074,41.105],[-5.92,36.344],[-10.448,4.467],[-4.887,-21.518],[-6.023,-31.818],[-6.023,-33.871],[-3.015,-38.892],[-0.719,-41.105],[8.779,-39.732],[10.447,-37.294],[9.861,-27.055],[1.872,3.44],[6.079,33.547],[1.477,40.944]],"c":true},"ix":2},"nm":"Path 1","mn":"ADBE Vector Shape - Group","hd":false},{"ty":"fl","c":{"a":0,"k":[0.666999966491,0.666999966491,0.666999966491,1],"ix":4},"o":{"a":0,"k":100,"ix":5},"r":1,"bm":0,"nm":"Fill 1","mn":"ADBE Vector Graphic - Fill","hd":false},{"ty":"tr","p":{"a":0,"k":[171.245,123.079],"ix":2},"a":{"a":0,"k":[0,0],"ix":1},"s":{"a":0,"k":[100,100],"ix":3},"r":{"a":0,"k":0,"ix":6},"o":{"a":0,"k":100,"ix":7},"sk":{"a":0,"k":0,"ix":4},"sa":{"a":0,"k":0,"ix":5},"nm":"Transform"}],"nm":"Group 91","np":2,"cix":2,"bm":0,"ix":10,"mn":"ADBE Vector Group","hd":false},{"ty":"gr","it":[{"ind":0,"ty":"sh","ix":1,"ks":{"a":0,"k":{"i":[[0,0],[0,0],[0,0],[0,0],[0,0]],"o":[[0,0],[0,0],[0,0],[0,0],[0,0]],"v":[[-5.069,27.123],[4.727,23.223],[5.069,14.544],[-3.915,-27.123],[-5.069,-27.123]],"c":true},"ix":2},"nm":"Path 1","mn":"ADBE Vector Shape - Group","hd":false},{"ty":"fl","c":{"a":0,"k":[0.677999997606,0.705999995213,0.728999956916,1],"ix":4},"o":{"a":0,"k":100,"ix":5},"r":1,"bm":0,"nm":"Fill 1","mn":"ADBE Vector Graphic - Fill","hd":false},{"ty":"tr","p":{"a":0,"k":[187.275,45.49],"ix":2},"a":{"a":0,"k":[0,0],"ix":1},"s":{"a":0,"k":[100,100],"ix":3},"r":{"a":0,"k":0,"ix":6},"o":{"a":0,"k":100,"ix":7},"sk":{"a":0,"k":0,"ix":4},"sa":{"a":0,"k":0,"ix":5},"nm":"Transform"}],"nm":"Group 92","np":2,"cix":2,"bm":0,"ix":11,"mn":"ADBE Vector Group","hd":false},{"ty":"gr","it":[{"ind":0,"ty":"sh","ix":1,"ks":{"a":0,"k":{"i":[[0,0],[0,0],[0,0],[0,0]],"o":[[0,0],[0,0],[0,0],[0,0]],"v":[[4.196,6.596],[-4.196,6.596],[-4.196,-2.757],[4.196,-6.596]],"c":true},"ix":2},"nm":"Path 1","mn":"ADBE Vector Shape - Group","hd":false},{"ty":"fl","c":{"a":0,"k":[0.677999997606,0.705999995213,0.728999956916,1],"ix":4},"o":{"a":0,"k":100,"ix":5},"r":1,"bm":0,"nm":"Fill 1","mn":"ADBE Vector Graphic - Fill","hd":false},{"ty":"tr","p":{"a":0,"k":[175.441,79.211],"ix":2},"a":{"a":0,"k":[0,0],"ix":1},"s":{"a":0,"k":[100,100],"ix":3},"r":{"a":0,"k":0,"ix":6},"o":{"a":0,"k":100,"ix":7},"sk":{"a":0,"k":0,"ix":4},"sa":{"a":0,"k":0,"ix":5},"nm":"Transform"}],"nm":"Group 93","np":2,"cix":2,"bm":0,"ix":12,"mn":"ADBE Vector Group","hd":false}],"ip":0,"op":602,"st":0,"bm":0},{"ddd":0,"ind":3,"ty":1,"nm":"Red Solid 2","sr":1,"ks":{"o":{"a":1,"k":[{"i":{"x":[0.667],"y":[1]},"o":{"x":[0.333],"y":[0]},"t":460,"s":[0]},{"i":{"x":[0.667],"y":[1]},"o":{"x":[0.333],"y":[0]},"t":483,"s":[100]},{"i":{"x":[0.667],"y":[1]},"o":{"x":[0.333],"y":[0]},"t":519,"s":[100]},{"t":556,"s":[0]}],"ix":11},"r":{"a":1,"k":[{"i":{"x":[0.667],"y":[1]},"o":{"x":[0.333],"y":[0]},"t":519,"s":[0]},{"t":556,"s":[-14]}],"ix":10},"p":{"a":1,"k":[{"i":{"x":0.667,"y":1},"o":{"x":0.333,"y":0},"t":460,"s":[185,139.5,0],"to":[0,10.833,0],"ti":[0,-10.833,0]},{"i":{"x":0.667,"y":0.667},"o":{"x":0.333,"y":0.333},"t":483,"s":[185,204.5,0],"to":[0,0,0],"ti":[0,0,0]},{"i":{"x":0.667,"y":1},"o":{"x":0.333,"y":0},"t":519,"s":[185,204.5,0],"to":[-6.667,16.667,0],"ti":[6.667,-16.667,0]},{"t":556,"s":[145,304.5,0]}],"ix":2},"a":{"a":0,"k":[300,300,0],"ix":1},"s":{"a":0,"k":[41,1.667,100],"ix":6}},"ao":0,"sw":600,"sh":600,"sc":"#cc203d","ip":388,"op":557,"st":388,"bm":0},{"ddd":0,"ind":4,"ty":1,"nm":"Red Solid 2","sr":1,"ks":{"o":{"a":1,"k":[{"i":{"x":[0.667],"y":[1]},"o":{"x":[0.333],"y":[0]},"t":460,"s":[0]},{"i":{"x":[0.667],"y":[1]},"o":{"x":[0.333],"y":[0]},"t":483,"s":[100]},{"i":{"x":[0.667],"y":[1]},"o":{"x":[0.333],"y":[0]},"t":519,"s":[100]},{"t":556,"s":[0]}],"ix":11},"r":{"a":1,"k":[{"i":{"x":[0.667],"y":[1]},"o":{"x":[0.333],"y":[0]},"t":519,"s":[0]},{"t":556,"s":[17]}],"ix":10},"p":{"a":1,"k":[{"i":{"x":0.667,"y":1},"o":{"x":0.333,"y":0},"t":460,"s":[429,139.5,0],"to":[0,10.833,0],"ti":[0,-10.833,0]},{"i":{"x":0.667,"y":0.667},"o":{"x":0.333,"y":0.333},"t":483,"s":[429,204.5,0],"to":[0,0,0],"ti":[0,0,0]},{"i":{"x":0.667,"y":1},"o":{"x":0.333,"y":0},"t":519,"s":[429,204.5,0],"to":[5.583,16.667,0],"ti":[-5.583,-16.667,0]},{"t":556,"s":[462.5,304.5,0]}],"ix":2},"a":{"a":0,"k":[300,300,0],"ix":1},"s":{"a":0,"k":[41,1.667,100],"ix":6}},"ao":0,"sw":600,"sh":600,"sc":"#cc203d","ip":388,"op":557,"st":388,"bm":0},{"ddd":0,"ind":5,"ty":1,"nm":"Red Solid 2","sr":1,"ks":{"o":{"a":1,"k":[{"i":{"x":[0.667],"y":[1]},"o":{"x":[0.333],"y":[0]},"t":343,"s":[0]},{"i":{"x":[0.667],"y":[1]},"o":{"x":[0.333],"y":[0]},"t":366,"s":[100]},{"i":{"x":[0.667],"y":[1]},"o":{"x":[0.333],"y":[0]},"t":402,"s":[100]},{"t":439,"s":[0]}],"ix":11},"r":{"a":1,"k":[{"i":{"x":[0.667],"y":[1]},"o":{"x":[0.333],"y":[0]},"t":402,"s":[0]},{"t":439,"s":[17]}],"ix":10},"p":{"a":1,"k":[{"i":{"x":0.667,"y":1},"o":{"x":0.333,"y":0},"t":343,"s":[429,139.5,0],"to":[0,10.833,0],"ti":[0,-10.833,0]},{"i":{"x":0.667,"y":0.667},"o":{"x":0.333,"y":0.333},"t":366,"s":[429,204.5,0],"to":[0,0,0],"ti":[0,0,0]},{"i":{"x":0.667,"y":1},"o":{"x":0.333,"y":0},"t":402,"s":[429,204.5,0],"to":[5.583,16.667,0],"ti":[-5.583,-16.667,0]},{"t":439,"s":[462.5,304.5,0]}],"ix":2},"a":{"a":0,"k":[300,300,0],"ix":1},"s":{"a":0,"k":[41,1.667,100],"ix":6}},"ao":0,"sw":600,"sh":600,"sc":"#cc203d","ip":271,"op":440,"st":271,"bm":0},{"ddd":0,"ind":6,"ty":1,"nm":"Red Solid 2","sr":1,"ks":{"o":{"a":1,"k":[{"i":{"x":[0.667],"y":[1]},"o":{"x":[0.333],"y":[0]},"t":343,"s":[0]},{"i":{"x":[0.667],"y":[1]},"o":{"x":[0.333],"y":[0]},"t":366,"s":[100]},{"i":{"x":[0.667],"y":[1]},"o":{"x":[0.333],"y":[0]},"t":402,"s":[100]},{"t":439,"s":[0]}],"ix":11},"r":{"a":1,"k":[{"i":{"x":[0.667],"y":[1]},"o":{"x":[0.333],"y":[0]},"t":402,"s":[0]},{"t":439,"s":[-14]}],"ix":10},"p":{"a":1,"k":[{"i":{"x":0.667,"y":1},"o":{"x":0.333,"y":0},"t":343,"s":[185,139.5,0],"to":[0,10.833,0],"ti":[0,-10.833,0]},{"i":{"x":0.667,"y":0.667},"o":{"x":0.333,"y":0.333},"t":366,"s":[185,204.5,0],"to":[0,0,0],"ti":[0,0,0]},{"i":{"x":0.667,"y":1},"o":{"x":0.333,"y":0},"t":402,"s":[185,204.5,0],"to":[-6.667,16.667,0],"ti":[6.667,-16.667,0]},{"t":439,"s":[145,304.5,0]}],"ix":2},"a":{"a":0,"k":[300,300,0],"ix":1},"s":{"a":0,"k":[41,1.667,100],"ix":6}},"ao":0,"sw":600,"sh":600,"sc":"#cc203d","ip":271,"op":440,"st":271,"bm":0},{"ddd":0,"ind":7,"ty":1,"nm":"Red Solid 2","sr":1,"ks":{"o":{"a":1,"k":[{"i":{"x":[0.667],"y":[1]},"o":{"x":[0.333],"y":[0]},"t":212,"s":[0]},{"i":{"x":[0.667],"y":[1]},"o":{"x":[0.333],"y":[0]},"t":235,"s":[100]},{"i":{"x":[0.667],"y":[1]},"o":{"x":[0.333],"y":[0]},"t":271,"s":[100]},{"t":308,"s":[0]}],"ix":11},"r":{"a":1,"k":[{"i":{"x":[0.667],"y":[1]},"o":{"x":[0.333],"y":[0]},"t":271,"s":[0]},{"t":308,"s":[17]}],"ix":10},"p":{"a":1,"k":[{"i":{"x":0.667,"y":1},"o":{"x":0.333,"y":0},"t":212,"s":[429,139.5,0],"to":[0,10.833,0],"ti":[0,-10.833,0]},{"i":{"x":0.667,"y":0.667},"o":{"x":0.333,"y":0.333},"t":235,"s":[429,204.5,0],"to":[0,0,0],"ti":[0,0,0]},{"i":{"x":0.667,"y":1},"o":{"x":0.333,"y":0},"t":271,"s":[429,204.5,0],"to":[5.583,16.667,0],"ti":[-5.583,-16.667,0]},{"t":308,"s":[462.5,304.5,0]}],"ix":2},"a":{"a":0,"k":[300,300,0],"ix":1},"s":{"a":0,"k":[41,1.667,100],"ix":6}},"ao":0,"sw":600,"sh":600,"sc":"#cc203d","ip":140,"op":309,"st":140,"bm":0},{"ddd":0,"ind":8,"ty":1,"nm":"Red Solid 2","sr":1,"ks":{"o":{"a":1,"k":[{"i":{"x":[0.667],"y":[1]},"o":{"x":[0.333],"y":[0]},"t":212,"s":[0]},{"i":{"x":[0.667],"y":[1]},"o":{"x":[0.333],"y":[0]},"t":235,"s":[100]},{"i":{"x":[0.667],"y":[1]},"o":{"x":[0.333],"y":[0]},"t":271,"s":[100]},{"t":308,"s":[0]}],"ix":11},"r":{"a":1,"k":[{"i":{"x":[0.667],"y":[1]},"o":{"x":[0.333],"y":[0]},"t":271,"s":[0]},{"t":308,"s":[-14]}],"ix":10},"p":{"a":1,"k":[{"i":{"x":0.667,"y":1},"o":{"x":0.333,"y":0},"t":212,"s":[185,139.5,0],"to":[0,10.833,0],"ti":[0,-10.833,0]},{"i":{"x":0.667,"y":0.667},"o":{"x":0.333,"y":0.333},"t":235,"s":[185,204.5,0],"to":[0,0,0],"ti":[0,0,0]},{"i":{"x":0.667,"y":1},"o":{"x":0.333,"y":0},"t":271,"s":[185,204.5,0],"to":[-6.667,16.667,0],"ti":[6.667,-16.667,0]},{"t":308,"s":[145,304.5,0]}],"ix":2},"a":{"a":0,"k":[300,300,0],"ix":1},"s":{"a":0,"k":[41,1.667,100],"ix":6}},"ao":0,"sw":600,"sh":600,"sc":"#cc203d","ip":140,"op":309,"st":140,"bm":0},{"ddd":0,"ind":9,"ty":1,"nm":"Red Solid 2","sr":1,"ks":{"o":{"a":1,"k":[{"i":{"x":[0.667],"y":[1]},"o":{"x":[0.333],"y":[0]},"t":72,"s":[0]},{"i":{"x":[0.667],"y":[1]},"o":{"x":[0.333],"y":[0]},"t":95,"s":[100]},{"i":{"x":[0.667],"y":[1]},"o":{"x":[0.333],"y":[0]},"t":131,"s":[100]},{"t":168,"s":[0]}],"ix":11},"r":{"a":1,"k":[{"i":{"x":[0.667],"y":[1]},"o":{"x":[0.333],"y":[0]},"t":131,"s":[0]},{"t":168,"s":[17]}],"ix":10},"p":{"a":1,"k":[{"i":{"x":0.667,"y":1},"o":{"x":0.333,"y":0},"t":72,"s":[429,139.5,0],"to":[0,10.833,0],"ti":[0,-10.833,0]},{"i":{"x":0.667,"y":0.667},"o":{"x":0.333,"y":0.333},"t":95,"s":[429,204.5,0],"to":[0,0,0],"ti":[0,0,0]},{"i":{"x":0.667,"y":1},"o":{"x":0.333,"y":0},"t":131,"s":[429,204.5,0],"to":[5.583,16.667,0],"ti":[-5.583,-16.667,0]},{"t":168,"s":[462.5,304.5,0]}],"ix":2},"a":{"a":0,"k":[300,300,0],"ix":1},"s":{"a":0,"k":[41,1.667,100],"ix":6}},"ao":0,"sw":600,"sh":600,"sc":"#cc203d","ip":0,"op":169,"st":0,"bm":0},{"ddd":0,"ind":10,"ty":1,"nm":"Red Solid 2","sr":1,"ks":{"o":{"a":1,"k":[{"i":{"x":[0.667],"y":[1]},"o":{"x":[0.333],"y":[0]},"t":72,"s":[0]},{"i":{"x":[0.667],"y":[1]},"o":{"x":[0.333],"y":[0]},"t":95,"s":[100]},{"i":{"x":[0.667],"y":[1]},"o":{"x":[0.333],"y":[0]},"t":131,"s":[100]},{"t":168,"s":[0]}],"ix":11},"r":{"a":1,"k":[{"i":{"x":[0.667],"y":[1]},"o":{"x":[0.333],"y":[0]},"t":131,"s":[0]},{"t":168,"s":[-14]}],"ix":10},"p":{"a":1,"k":[{"i":{"x":0.667,"y":1},"o":{"x":0.333,"y":0},"t":72,"s":[185,139.5,0],"to":[0,10.833,0],"ti":[0,-10.833,0]},{"i":{"x":0.667,"y":0.667},"o":{"x":0.333,"y":0.333},"t":95,"s":[185,204.5,0],"to":[0,0,0],"ti":[0,0,0]},{"i":{"x":0.667,"y":1},"o":{"x":0.333,"y":0},"t":131,"s":[185,204.5,0],"to":[-6.667,16.667,0],"ti":[6.667,-16.667,0]},{"t":168,"s":[145,304.5,0]}],"ix":2},"a":{"a":0,"k":[300,300,0],"ix":1},"s":{"a":0,"k":[41,1.667,100],"ix":6}},"ao":0,"sw":600,"sh":600,"sc":"#cc203d","ip":0,"op":169,"st":0,"bm":0},{"ddd":0,"ind":11,"ty":4,"nm":"OBJECTS/124372-OQT5KA-344 Outlines","sr":1,"ks":{"o":{"a":1,"k":[{"i":{"x":[0.667],"y":[1]},"o":{"x":[0.333],"y":[0]},"t":25,"s":[0]},{"i":{"x":[0.57],"y":[1]},"o":{"x":[0.194],"y":[0]},"t":68,"s":[100]},{"i":{"x":[0.663],"y":[1]},"o":{"x":[0.329],"y":[0]},"t":271,"s":[100]},{"i":{"x":[0.704],"y":[1]},"o":{"x":[0.336],"y":[0]},"t":299,"s":[0]},{"i":{"x":[0.667],"y":[1]},"o":{"x":[0.333],"y":[0]},"t":574,"s":[100]},{"t":599,"s":[0]}],"ix":11},"r":{"a":1,"k":[{"i":{"x":[0.667],"y":[1]},"o":{"x":[0.333],"y":[0]},"t":26,"s":[0]},{"i":{"x":[0.833],"y":[1]},"o":{"x":[0.167],"y":[0]},"t":47,"s":[-22]},{"i":{"x":[0.833],"y":[1]},"o":{"x":[0.167],"y":[0]},"t":106,"s":[-22]},{"i":{"x":[0.833],"y":[1]},"o":{"x":[0.167],"y":[0]},"t":131,"s":[0]},{"i":{"x":[0.833],"y":[1]},"o":{"x":[0.167],"y":[0]},"t":156,"s":[-22]},{"i":{"x":[0.833],"y":[1]},"o":{"x":[0.167],"y":[0]},"t":242,"s":[-22]},{"i":{"x":[0.833],"y":[1]},"o":{"x":[0.167],"y":[0]},"t":267,"s":[0]},{"i":{"x":[0.833],"y":[1]},"o":{"x":[0.167],"y":[0]},"t":292,"s":[-22]},{"i":{"x":[0.833],"y":[1]},"o":{"x":[0.167],"y":[0]},"t":366,"s":[-22]},{"i":{"x":[0.833],"y":[1]},"o":{"x":[0.167],"y":[0]},"t":391,"s":[0]},{"i":{"x":[0.833],"y":[1]},"o":{"x":[0.167],"y":[0]},"t":416,"s":[-22]},{"i":{"x":[0.833],"y":[1]},"o":{"x":[0.167],"y":[0]},"t":486,"s":[-22]},{"i":{"x":[0.833],"y":[1]},"o":{"x":[0.167],"y":[0]},"t":511,"s":[0]},{"t":536,"s":[-22]}],"ix":10},"p":{"a":1,"k":[{"i":{"x":0.667,"y":1},"o":{"x":0.333,"y":0},"t":271,"s":[306.5,263.5,0],"to":[0,0,0],"ti":[0,0,0]},{"i":{"x":0.667,"y":1},"o":{"x":0.333,"y":0},"t":299,"s":[306.5,334,0],"to":[0,0,0],"ti":[0,0,0]},{"i":{"x":0.667,"y":1},"o":{"x":0.333,"y":0},"t":574,"s":[306.5,263.5,0],"to":[0,8.333,0],"ti":[0,-8.333,0]},{"t":599,"s":[306.5,313.5,0]}],"ix":2},"a":{"a":0,"k":[322.865,73.657,0],"ix":1},"s":{"a":0,"k":[162.279,162.279,100],"ix":6}},"ao":0,"shapes":[{"ty":"gr","it":[{"ind":0,"ty":"sh","ix":1,"ks":{"a":0,"k":{"i":[[0,0],[-11.774,26.268],[30.047,-9.446],[-17.302,18.855],[25.212,0.615],[-18.179,8.123],[20.506,7.719],[-15.138,-0.063],[11.712,7.163],[-3.665,-2.256],[3.584,3.661],[0.901,-0.26],[-0.057,1.328],[0,0],[-3.828,43.457],[25.4,-18.676]],"o":[[29.731,-16.121],[10.375,35.687],[23.009,-2.264],[-1.155,30.221],[16.75,3.325],[-10.291,21.511],[11.145,5.914],[-11.381,9.588],[2.778,2.544],[-5.96,0.916],[-0.553,2.439],[1.561,-8.839],[0.058,-1.329],[40.464,-24.638],[21.682,30.601],[0,0]],"v":[[-16.957,24.953],[33.332,-32.193],[-27.418,33.35],[30.477,2.453],[-33.482,36.828],[17.423,29.461],[-39.444,39.202],[-0.655,47.791],[-36.719,47.502],[-27.074,54.663],[-41.487,49.584],[-43.707,54.245],[-43.186,40.264],[-41.799,37.837],[19.676,-57.379],[-16.964,24.955]],"c":true},"ix":2},"nm":"Path 1","mn":"ADBE Vector Shape - Group","hd":false},{"ty":"fl","c":{"a":0,"k":[1,1,1,1],"ix":4},"o":{"a":0,"k":100,"ix":5},"r":1,"bm":0,"nm":"Fill 1","mn":"ADBE Vector Graphic - Fill","hd":false},{"ty":"tr","p":{"a":0,"k":[392.245,103.176],"ix":2},"a":{"a":0,"k":[0,0],"ix":1},"s":{"a":0,"k":[100,100],"ix":3},"r":{"a":0,"k":0,"ix":6},"o":{"a":0,"k":100,"ix":7},"sk":{"a":0,"k":0,"ix":4},"sa":{"a":0,"k":0,"ix":5},"nm":"Transform"}],"nm":"Group 8","np":2,"cix":2,"bm":0,"ix":1,"mn":"ADBE Vector Group","hd":false}],"ip":0,"op":602,"st":0,"bm":0},{"ddd":0,"ind":12,"ty":4,"nm":"Layer 1/6039 [Converted] Outlines","sr":1,"ks":{"o":{"a":1,"k":[{"i":{"x":[0.667],"y":[1]},"o":{"x":[0.333],"y":[0]},"t":0,"s":[0]},{"i":{"x":[0.572],"y":[1]},"o":{"x":[0.189],"y":[0]},"t":25,"s":[100]},{"i":{"x":[0.664],"y":[1]},"o":{"x":[0.331],"y":[0]},"t":271,"s":[100]},{"i":{"x":[0.703],"y":[1]},"o":{"x":[0.34],"y":[0]},"t":299,"s":[0]},{"i":{"x":[0.667],"y":[1]},"o":{"x":[0.333],"y":[0]},"t":574,"s":[100]},{"t":599,"s":[0]}],"ix":11},"r":{"a":1,"k":[{"i":{"x":[0.667],"y":[1]},"o":{"x":[0.333],"y":[0]},"t":26,"s":[0]},{"i":{"x":[0.833],"y":[1]},"o":{"x":[0.167],"y":[0]},"t":47,"s":[20]},{"i":{"x":[0.833],"y":[1]},"o":{"x":[0.167],"y":[0]},"t":106,"s":[20]},{"i":{"x":[0.833],"y":[1]},"o":{"x":[0.167],"y":[0]},"t":131,"s":[0]},{"i":{"x":[0.833],"y":[1]},"o":{"x":[0.167],"y":[0]},"t":156,"s":[20]},{"i":{"x":[0.833],"y":[1]},"o":{"x":[0.167],"y":[0]},"t":242,"s":[20]},{"i":{"x":[0.833],"y":[1]},"o":{"x":[0.167],"y":[0]},"t":267,"s":[0]},{"i":{"x":[0.833],"y":[1]},"o":{"x":[0.167],"y":[0]},"t":292,"s":[20]},{"i":{"x":[0.833],"y":[1]},"o":{"x":[0.167],"y":[0]},"t":366,"s":[20]},{"i":{"x":[0.833],"y":[1]},"o":{"x":[0.167],"y":[0]},"t":391,"s":[0]},{"i":{"x":[0.833],"y":[1]},"o":{"x":[0.167],"y":[0]},"t":416,"s":[20]},{"i":{"x":[0.833],"y":[1]},"o":{"x":[0.167],"y":[0]},"t":486,"s":[20]},{"i":{"x":[0.833],"y":[1]},"o":{"x":[0.167],"y":[0]},"t":511,"s":[0]},{"t":536,"s":[20]}],"ix":10},"p":{"a":1,"k":[{"i":{"x":0.667,"y":1},"o":{"x":0.333,"y":0},"t":0,"s":[308.5,425,0],"to":[0,-26.833,0],"ti":[0,26.833,0]},{"i":{"x":0.572,"y":0.572},"o":{"x":0.189,"y":0.189},"t":25,"s":[308.5,264,0],"to":[0,0,0],"ti":[0,0,0]},{"i":{"x":0.664,"y":1},"o":{"x":0.331,"y":0},"t":271,"s":[308.5,264,0],"to":[0,0,0],"ti":[0,0,0]},{"i":{"x":0.703,"y":1},"o":{"x":0.34,"y":0},"t":299,"s":[308.5,334.5,0],"to":[0,0,0],"ti":[0,0,0]},{"i":{"x":0.667,"y":1},"o":{"x":0.333,"y":0},"t":574,"s":[308.5,264,0],"to":[0,8.333,0],"ti":[0,-8.333,0]},{"t":599,"s":[308.5,314,0]}],"ix":2},"a":{"a":0,"k":[181.23,71.541,0],"ix":1},"s":{"a":0,"k":[182.417,182.417,100],"ix":6}},"ao":0,"shapes":[{"ty":"gr","it":[{"ind":0,"ty":"sh","ix":1,"ks":{"a":0,"k":{"i":[[0.544,2.333],[0,21.464],[-2.384,7.777],[1.068,0.323],[0,-11.716],[-0.185,-0.792],[-2.798,0],[-0.47,0.109],[-0.045,0.011]],"o":[[-0.185,-0.792],[0,-11.107],[-0.665,-0.558],[-2.457,8.455],[0,21.464],[0.663,2.843],[0.463,0],[0.045,-0.011],[-2.175,-0.539]],"v":[[1.499,26.55],[-3.029,-5.326],[2.144,-30.018],[-0.468,-31.312],[-6.029,-5.326],[-1.501,26.55],[4.492,31.312],[5.895,31.15],[6.028,31.113]],"c":true},"ix":2},"nm":"Path 1","mn":"ADBE Vector Shape - Group","hd":false},{"ty":"fl","c":{"a":0,"k":[0.019999999626,0.035000000748,0.059000000299,1],"ix":4},"o":{"a":0,"k":100,"ix":5},"r":1,"bm":0,"nm":"Fill 1","mn":"ADBE Vector Graphic - Fill","hd":false},{"ty":"tr","p":{"a":0,"k":[166.826,132.873],"ix":2},"a":{"a":0,"k":[0,0],"ix":1},"s":{"a":0,"k":[100,100],"ix":3},"r":{"a":0,"k":0,"ix":6},"o":{"a":0,"k":100,"ix":7},"sk":{"a":0,"k":0,"ix":4},"sa":{"a":0,"k":0,"ix":5},"nm":"Transform"}],"nm":"Group 82","np":2,"cix":2,"bm":0,"ix":1,"mn":"ADBE Vector Group","hd":false},{"ty":"gr","it":[{"ind":0,"ty":"sh","ix":1,"ks":{"a":0,"k":{"i":[[-0.185,-0.792],[-2.798,0],[-0.47,0.109],[0.77,3.314],[0.464,1.536],[1.211,6.816],[0,8.743],[-1.498,4.691],[3.481,1.053],[0,-11.716]],"o":[[0.663,2.843],[0.463,0],[3.312,-0.773],[-0.012,-0.05],[-4.264,1.281],[-0.883,-4.971],[0,-6.967],[1.562,-4.891],[-2.457,8.455],[0,21.464]],"v":[[-4.12,26.55],[1.872,31.312],[3.275,31.15],[7.878,23.753],[7.077,21.374],[-0.849,14.667],[-2.489,-5.84],[0.332,-23.372],[-3.088,-31.312],[-8.648,-5.326]],"c":true},"ix":2},"nm":"Path 1","mn":"ADBE Vector Shape - Group","hd":false},{"ty":"fl","c":{"a":0,"k":[0.059000000299,0.109999997008,0.19199999641,1],"ix":4},"o":{"a":0,"k":100,"ix":5},"r":1,"bm":0,"nm":"Fill 1","mn":"ADBE Vector Graphic - Fill","hd":false},{"ty":"tr","p":{"a":0,"k":[169.446,132.873],"ix":2},"a":{"a":0,"k":[0,0],"ix":1},"s":{"a":0,"k":[100,100],"ix":3},"r":{"a":0,"k":0,"ix":6},"o":{"a":0,"k":100,"ix":7},"sk":{"a":0,"k":0,"ix":4},"sa":{"a":0,"k":0,"ix":5},"nm":"Transform"}],"nm":"Group 83","np":2,"cix":2,"bm":0,"ix":2,"mn":"ADBE Vector Group","hd":false},{"ty":"gr","it":[{"ind":0,"ty":"sh","ix":1,"ks":{"a":0,"k":{"i":[[-0.062,0.266],[-0.084,2.463],[2.359,0],[0,-1.712],[0,-0.754],[0,0],[1.522,-5.237],[0,-11.716],[-0.184,-0.792],[-2.799,0],[-0.469,0.11],[-0.402,0.195],[0,21.107]],"o":[[0.383,-1.633],[-1.765,-0.48],[-1.118,0],[0,1.955],[0,0],[0,0.385],[-2.457,8.456],[0,21.464],[0.664,2.843],[0.463,0],[0.454,-0.105],[-1.111,-3.144],[0,-20.635]],"v":[[8.764,-33.332],[9.41,-39.856],[0.32,-41.105],[-1.976,-38.893],[-4.985,-33.871],[-4.985,-31.818],[-3.848,-21.519],[-9.41,4.467],[-4.882,36.344],[1.112,41.105],[2.514,40.943],[3.797,40.486],[-1.078,4.237]],"c":true},"ix":2},"nm":"Path 1","mn":"ADBE Vector Shape - Group","hd":false},{"ty":"fl","c":{"a":0,"k":[1,1,1,1],"ix":4},"o":{"a":0,"k":100,"ix":5},"r":1,"bm":0,"nm":"Fill 1","mn":"ADBE Vector Graphic - Fill","hd":false},{"ty":"tr","p":{"a":0,"k":[170.207,123.08],"ix":2},"a":{"a":0,"k":[0,0],"ix":1},"s":{"a":0,"k":[100,100],"ix":3},"r":{"a":0,"k":0,"ix":6},"o":{"a":0,"k":100,"ix":7},"sk":{"a":0,"k":0,"ix":4},"sa":{"a":0,"k":0,"ix":5},"nm":"Transform"}],"nm":"Group 84","np":2,"cix":2,"bm":0,"ix":3,"mn":"ADBE Vector Group","hd":false},{"ty":"gr","it":[{"ind":0,"ty":"sh","ix":1,"ks":{"a":0,"k":{"i":[[0.211,-12.255],[0,0],[0,0],[0,0],[0,0]],"o":[[0,0],[0,0],[0,0],[0,0],[3.358,16.887]],"v":[[3.701,25.29],[4.29,25.056],[4.633,16.377],[-4.351,-25.29],[-4.632,-25.29]],"c":true},"ix":2},"nm":"Path 1","mn":"ADBE Vector Shape - Group","hd":false},{"ty":"fl","c":{"a":0,"k":[0.552999997606,0.57599995931,0.6,1],"ix":4},"o":{"a":0,"k":100,"ix":5},"r":1,"bm":0,"nm":"Fill 1","mn":"ADBE Vector Graphic - Fill","hd":false},{"ty":"tr","p":{"a":0,"k":[187.712,43.657],"ix":2},"a":{"a":0,"k":[0,0],"ix":1},"s":{"a":0,"k":[100,100],"ix":3},"r":{"a":0,"k":0,"ix":6},"o":{"a":0,"k":100,"ix":7},"sk":{"a":0,"k":0,"ix":4},"sa":{"a":0,"k":0,"ix":5},"nm":"Transform"}],"nm":"Group 85","np":2,"cix":2,"bm":0,"ix":4,"mn":"ADBE Vector Group","hd":false},{"ty":"gr","it":[{"ind":0,"ty":"sh","ix":1,"ks":{"a":0,"k":{"i":[[0,-2.209],[2.209,0],[0,2.209],[-2.209,0]],"o":[[0,2.209],[-2.209,0],[0,-2.209],[2.209,0]],"v":[[4,0],[0,4],[-4,0],[0,-4]],"c":true},"ix":2},"nm":"Path 1","mn":"ADBE Vector Shape - Group","hd":false},{"ty":"fl","c":{"a":0,"k":[0.677999997606,0.705999995213,0.728999956916,1],"ix":4},"o":{"a":0,"k":100,"ix":5},"r":1,"bm":0,"nm":"Fill 1","mn":"ADBE Vector Graphic - Fill","hd":false},{"ty":"tr","p":{"a":0,"k":[181.692,71.559],"ix":2},"a":{"a":0,"k":[0,0],"ix":1},"s":{"a":0,"k":[100,100],"ix":3},"r":{"a":0,"k":0,"ix":6},"o":{"a":0,"k":100,"ix":7},"sk":{"a":0,"k":0,"ix":4},"sa":{"a":0,"k":0,"ix":5},"nm":"Transform"}],"nm":"Group 86","np":2,"cix":2,"bm":0,"ix":5,"mn":"ADBE Vector Group","hd":false},{"ty":"gr","it":[{"ind":0,"ty":"sh","ix":1,"ks":{"a":0,"k":{"i":[[2.757,0],[0,2.758],[-2.757,0],[0,-2.758]],"o":[[-2.757,0],[0,-2.758],[2.757,0],[0,2.758]],"v":[[0,5],[-5,0],[0,-5],[5,0]],"c":true},"ix":2},"nm":"Path 1","mn":"ADBE Vector Shape - Group","hd":false},{"ty":"fl","c":{"a":0,"k":[0.552999997606,0.57599995931,0.6,1],"ix":4},"o":{"a":0,"k":100,"ix":5},"r":1,"bm":0,"nm":"Fill 1","mn":"ADBE Vector Graphic - Fill","hd":false},{"ty":"tr","p":{"a":0,"k":[181.692,71.559],"ix":2},"a":{"a":0,"k":[0,0],"ix":1},"s":{"a":0,"k":[100,100],"ix":3},"r":{"a":0,"k":0,"ix":6},"o":{"a":0,"k":100,"ix":7},"sk":{"a":0,"k":0,"ix":4},"sa":{"a":0,"k":0,"ix":5},"nm":"Transform"}],"nm":"Group 87","np":2,"cix":2,"bm":0,"ix":6,"mn":"ADBE Vector Group","hd":false},{"ty":"gr","it":[{"ind":0,"ty":"sh","ix":1,"ks":{"a":0,"k":{"i":[[0,-5.215],[5.215,0],[0,5.215],[-5.215,0]],"o":[[0,5.215],[-5.215,0],[0,-5.215],[5.215,0]],"v":[[9.443,0],[0,9.443],[-9.443,0],[0,-9.443]],"c":true},"ix":2},"nm":"Path 1","mn":"ADBE Vector Shape - Group","hd":false},{"ty":"fl","c":{"a":0,"k":[0.677999997606,0.705999995213,0.728999956916,1],"ix":4},"o":{"a":0,"k":100,"ix":5},"r":1,"bm":0,"nm":"Fill 1","mn":"ADBE Vector Graphic - Fill","hd":false},{"ty":"tr","p":{"a":0,"k":[181.692,71.559],"ix":2},"a":{"a":0,"k":[0,0],"ix":1},"s":{"a":0,"k":[100,100],"ix":3},"r":{"a":0,"k":0,"ix":6},"o":{"a":0,"k":100,"ix":7},"sk":{"a":0,"k":0,"ix":4},"sa":{"a":0,"k":0,"ix":5},"nm":"Transform"}],"nm":"Group 88","np":2,"cix":2,"bm":0,"ix":7,"mn":"ADBE Vector Group","hd":false},{"ty":"gr","it":[{"ind":0,"ty":"sh","ix":1,"ks":{"a":0,"k":{"i":[[4.578,0.224],[0,0],[0,0]],"o":[[0,0],[0,0],[-1.167,-4.268]],"v":[[-4.775,-5.736],[-4.775,5.736],[4.775,1.932]],"c":true},"ix":2},"nm":"Path 1","mn":"ADBE Vector Shape - Group","hd":false},{"ty":"fl","c":{"a":0,"k":[0.552999997606,0.57599995931,0.6,1],"ix":4},"o":{"a":0,"k":100,"ix":5},"r":1,"bm":0,"nm":"Fill 1","mn":"ADBE Vector Graphic - Fill","hd":false},{"ty":"tr","p":{"a":0,"k":[186.981,66.878],"ix":2},"a":{"a":0,"k":[0,0],"ix":1},"s":{"a":0,"k":[100,100],"ix":3},"r":{"a":0,"k":0,"ix":6},"o":{"a":0,"k":100,"ix":7},"sk":{"a":0,"k":0,"ix":4},"sa":{"a":0,"k":0,"ix":5},"nm":"Transform"}],"nm":"Group 89","np":2,"cix":2,"bm":0,"ix":8,"mn":"ADBE Vector Group","hd":false},{"ty":"gr","it":[{"ind":0,"ty":"sh","ix":1,"ks":{"a":0,"k":{"i":[[-3.278,-0.657],[0,0],[0,0]],"o":[[0,0],[0,0],[1.39,2.948]],"v":[[3.693,4.592],[3.693,-4.592],[-3.693,-1.213]],"c":true},"ix":2},"nm":"Path 1","mn":"ADBE Vector Shape - Group","hd":false},{"ty":"fl","c":{"a":0,"k":[0.552999997606,0.57599995931,0.6,1],"ix":4},"o":{"a":0,"k":100,"ix":5},"r":1,"bm":0,"nm":"Fill 1","mn":"ADBE Vector Graphic - Fill","hd":false},{"ty":"tr","p":{"a":0,"k":[175.944,77.206],"ix":2},"a":{"a":0,"k":[0,0],"ix":1},"s":{"a":0,"k":[100,100],"ix":3},"r":{"a":0,"k":0,"ix":6},"o":{"a":0,"k":100,"ix":7},"sk":{"a":0,"k":0,"ix":4},"sa":{"a":0,"k":0,"ix":5},"nm":"Transform"}],"nm":"Group 90","np":2,"cix":2,"bm":0,"ix":9,"mn":"ADBE Vector Group","hd":false},{"ty":"gr","it":[{"ind":0,"ty":"sh","ix":1,"ks":{"a":0,"k":{"i":[[0.463,0],[0.663,2.843],[0,21.464],[-2.457,8.455],[0,0.386],[0,0],[0,1.954],[-1.117,0],[-1.236,-0.456],[0,-1.544],[0.586,-2.496],[0,-16.75],[-0.043,-0.18],[3.312,-0.773]],"o":[[-2.798,0],[-0.185,-0.792],[0,-11.716],[1.522,-5.237],[0,0],[0,-0.753],[0,-1.713],[2.574,0],[0.89,0.329],[0,2.961],[-0.05,0.216],[0,19.993],[0.769,3.314],[-0.47,0.109]],"v":[[0.074,41.105],[-5.92,36.344],[-10.448,4.467],[-4.887,-21.518],[-6.023,-31.818],[-6.023,-33.871],[-3.015,-38.892],[-0.719,-41.105],[8.779,-39.732],[10.447,-37.294],[9.861,-27.055],[1.872,3.44],[6.079,33.547],[1.477,40.944]],"c":true},"ix":2},"nm":"Path 1","mn":"ADBE Vector Shape - Group","hd":false},{"ty":"fl","c":{"a":0,"k":[0.666999966491,0.666999966491,0.666999966491,1],"ix":4},"o":{"a":0,"k":100,"ix":5},"r":1,"bm":0,"nm":"Fill 1","mn":"ADBE Vector Graphic - Fill","hd":false},{"ty":"tr","p":{"a":0,"k":[171.245,123.079],"ix":2},"a":{"a":0,"k":[0,0],"ix":1},"s":{"a":0,"k":[100,100],"ix":3},"r":{"a":0,"k":0,"ix":6},"o":{"a":0,"k":100,"ix":7},"sk":{"a":0,"k":0,"ix":4},"sa":{"a":0,"k":0,"ix":5},"nm":"Transform"}],"nm":"Group 91","np":2,"cix":2,"bm":0,"ix":10,"mn":"ADBE Vector Group","hd":false},{"ty":"gr","it":[{"ind":0,"ty":"sh","ix":1,"ks":{"a":0,"k":{"i":[[0,0],[0,0],[0,0],[0,0],[0,0]],"o":[[0,0],[0,0],[0,0],[0,0],[0,0]],"v":[[-5.069,27.123],[4.727,23.223],[5.069,14.544],[-3.915,-27.123],[-5.069,-27.123]],"c":true},"ix":2},"nm":"Path 1","mn":"ADBE Vector Shape - Group","hd":false},{"ty":"fl","c":{"a":0,"k":[0.677999997606,0.705999995213,0.728999956916,1],"ix":4},"o":{"a":0,"k":100,"ix":5},"r":1,"bm":0,"nm":"Fill 1","mn":"ADBE Vector Graphic - Fill","hd":false},{"ty":"tr","p":{"a":0,"k":[187.275,45.49],"ix":2},"a":{"a":0,"k":[0,0],"ix":1},"s":{"a":0,"k":[100,100],"ix":3},"r":{"a":0,"k":0,"ix":6},"o":{"a":0,"k":100,"ix":7},"sk":{"a":0,"k":0,"ix":4},"sa":{"a":0,"k":0,"ix":5},"nm":"Transform"}],"nm":"Group 92","np":2,"cix":2,"bm":0,"ix":11,"mn":"ADBE Vector Group","hd":false},{"ty":"gr","it":[{"ind":0,"ty":"sh","ix":1,"ks":{"a":0,"k":{"i":[[0,0],[0,0],[0,0],[0,0]],"o":[[0,0],[0,0],[0,0],[0,0]],"v":[[4.196,6.596],[-4.196,6.596],[-4.196,-2.757],[4.196,-6.596]],"c":true},"ix":2},"nm":"Path 1","mn":"ADBE Vector Shape - Group","hd":false},{"ty":"fl","c":{"a":0,"k":[0.677999997606,0.705999995213,0.728999956916,1],"ix":4},"o":{"a":0,"k":100,"ix":5},"r":1,"bm":0,"nm":"Fill 1","mn":"ADBE Vector Graphic - Fill","hd":false},{"ty":"tr","p":{"a":0,"k":[175.441,79.211],"ix":2},"a":{"a":0,"k":[0,0],"ix":1},"s":{"a":0,"k":[100,100],"ix":3},"r":{"a":0,"k":0,"ix":6},"o":{"a":0,"k":100,"ix":7},"sk":{"a":0,"k":0,"ix":4},"sa":{"a":0,"k":0,"ix":5},"nm":"Transform"}],"nm":"Group 93","np":2,"cix":2,"bm":0,"ix":12,"mn":"ADBE Vector Group","hd":false}],"ip":0,"op":602,"st":0,"bm":0}],"markers":[]}